scratch2py/__init__.py
scratch2py-0.6.7.dist-info/LICENSE
scratch2py-0.6.7.dist-info/METADATA
scratch2py-0.6.7.dist-info/WHEEL
scratch2py-0.6.7.dist-info/top_level.txt
scratch2py-0.6.7.dist-info/RECORD
