Metadata-Version: 2.1
Name: scratch2py
Version: 0.6.7
Summary: Python to Scratch API connector
Home-page: https://github.com/The-Cloud-Dev/scratch2py
Author: TheCloudDev
License: MIT
Platform: UNKNOWN
Classifier: Programming Language :: Python :: 3
Classifier: License :: OSI Approved :: MIT License
Classifier: Operating System :: OS Independent
Requires-Python: >=3.6
License-File: LICENSE
Requires-Dist: websocket-client
Requires-Dist: ScratchEncoder
Requires-Dist: requests
